{
  "project_info": {
    "project_number": "1013130494905",
    "firebase_url": "https://gde-ttb.firebaseio.com",
    "project_id": "gde-ttb",
    "storage_bucket": "gde-ttb.appspot.com"
  },
  "client": [
    {
      "client_info": {
        "mobilesdk_app_id": "1:1013130494905:android:3298283f475cf85bb2ec68",
        "android_client_info": {
          "package_name": "com.ttb.android"
        }
      },
      "oauth_client": [
        {
          "client_id": "1013130494905-f7bog8o5k72ebpin62slmhq0hno4r856.apps.googleusercontent.com",
          "client_type": 1,
          "android_info": {
            "package_name": "com.ttb.android",
            "certificate_hash": "66f3a2b27e8eee6fc7a7e2e2b75e1cc1c005fb25"
          }
        },
        {
          "client_id": "1013130494905-s5gfg697rtukk3h8f7qkpp2lma61jfpo.apps.googleusercontent.com",
          "client_type": 1,
          "android_info": {
            "package_name": "com.ttb.android",
            "certificate_hash": "38a61a5a0ed3e82e9c20fa5ffe4e56c71ee0b22e"
          }
        },
        {
          "client_id": "1013130494905-g9da8erm4kcv3agh5t7jab5sfh47l41o.apps.googleusercontent.com",
          "client_type": 1,
          "android_info": {
            "package_name": "com.ttb.android",
            "certificate_hash": "843046aeea54ed8dba79ef50a489947bedaf3d5b"
          }
        },
        {
          "client_id": "1013130494905-hh7c4ldebguvujqf95hp3f8evtj38tgt.apps.googleusercontent.com",
          "client_type": 3
        }
      ],
      "api_key": [
        {
          "current_key": "AIzaSyBSGlSsp3Meirjhahe9ptshK4WPENuDbUc"
        }
      ],
      "services": {
        "appinvite_service": {
          "other_platform_oauth_client": [
            {
              "client_id": "1013130494905-hh7c4ldebguvujqf95hp3f8evtj38tgt.apps.googleusercontent.com",
              "client_type": 3
            },
            {
              "client_id": "1013130494905-bicbb9near6ierpu1ksjjot24arbohhl.apps.googleusercontent.com",
              "client_type": 2,
              "ios_info": {
                "bundle_id": "com.ttb.ios"
              }
            }
          ]
        }
      }
    }
  ],
  "configuration_version": "1"
}